vib_analysis/__init__.py
vib_analysis/api.py
vib_analysis/characterize.py
vib_analysis/cli.py
vib_analysis/config.py
vib_analysis/convert.py
vib_analysis/core.py
vib_analysis/graph_compare.py
vib_analysis/output.py
vib_analysis/utils.py
vib_analysis-1.3.0.dist-info/licenses/LICENSE
vib_analysis-1.3.0.dist-info/METADATA
vib_analysis-1.3.0.dist-info/WHEEL
vib_analysis-1.3.0.dist-info/entry_points.txt
vib_analysis-1.3.0.dist-info/top_level.txt
vib_analysis-1.3.0.dist-info/RECORD
