Metadata-Version: 2.4
Name: vib_analysis
Version: 1.3.0
Summary: Internal Coordinate Analysis of Vibrational Modes.
Author: Dr Alister Goodfellow
Project-URL: homepage, https://github.com/aligfellow/vib_analysis
Classifier: Programming Language :: Python :: 3
Classifier: License :: OSI Approved :: MIT License
Classifier: Operating System :: OS Independent
Requires-Python: >=3.8
License-File: LICENSE
Requires-Dist: numpy
Requires-Dist: cclib
Requires-Dist: networkx
Requires-Dist: xyzgraph
Dynamic: license-file
